CHANGES.rst
MANIFEST.in
README.rst
setup.cfg
setup.py
djmemcache/__init__.py
djmemcache/backend.py
djmemcache/client.py
djmemcache.egg-info/PKG-INFO
djmemcache.egg-info/SOURCES.txt
djmemcache.egg-info/dependency_links.txt
djmemcache.egg-info/not-zip-safe
djmemcache.egg-info/requires.txt
djmemcache.egg-info/top_level.txt