Metadata-Version: 1.1
Name: djmemcache
Version: 0.8
Summary: A Memcached Pool for Django
Home-page: https://github.com/duanhongyi/django-pymemcache-pool
Author: Duan Hongyi
Author-email: duanhongyi@doopai.com
License: UNKNOWN
Keywords: django pymemcache pool
Platform: UNKNOWN
Classifier: Programming Language :: Python
Classifier: Framework :: Pylons
Classifier: Topic :: Internet :: WWW/HTTP
Classifier: Topic :: Internet :: WWW/HTTP :: WSGI :: Application
Classifier: License :: OSI Approved :: Apache Software License
